{
  "built": "2026-07-03T10:41:49.340Z",
  "note": "48 qualified WC2026 teams",
  "ratings": {
    "australia": 1786,
    "iran": 1749,
    "iraq": 1546,
    "japan": 1868,
    "jordan": 1543,
    "qatar": 1482,
    "saudi-arabia": 1628,
    "south-korea": 1733,
    "uzbekistan": 1593,
    "algeria": 1711,
    "cape-verde": 1613,
    "dr-congo": 1663,
    "egypt": 1732,
    "ghana": 1645,
    "ivory-coast": 1758,
    "morocco": 1922,
    "senegal": 1812,
    "south-africa": 1597,
    "tunisia": 1609,
    "canada": 1746,
    "curacao": 1525,
    "haiti": 1515,
    "mexico": 1899,
    "panama": 1595,
    "usa": 1814,
    "argentina": 2075,
    "brazil": 1997,
    "colombia": 1909,
    "ecuador": 1794,
    "paraguay": 1713,
    "uruguay": 1789,
    "new-zealand": 1576,
    "austria": 1758,
    "belgium": 1882,
    "bosnia-and-herzegovina": 1589,
    "croatia": 1861,
    "czech-republic": 1621,
    "england": 2000,
    "france": 2067,
    "germany": 1913,
    "netherlands": 1948,
    "norway": 1851,
    "portugal": 1937,
    "scotland": 1649,
    "spain": 2099,
    "sweden": 1661,
    "switzerland": 1861,
    "turkey": 1749
  }
}